kmeans_seeding/__init__.py
kmeans_seeding/_core.cpython-313-darwin.so
kmeans_seeding/initializers.py
kmeans_seeding-0.2.3.dist-info/licenses/LICENSE
kmeans_seeding-0.2.3.dist-info/METADATA
kmeans_seeding-0.2.3.dist-info/WHEEL
kmeans_seeding-0.2.3.dist-info/top_level.txt
kmeans_seeding-0.2.3.dist-info/RECORD
