Metadata-Version: 2.4
Name: kmeans-seeding
Version: 0.2.3
Summary: Fast k-means++ seeding algorithms with C++ implementation and Python bindings
Author-email: Poojan Shah <cs1221594@cse.iitd.ac.in>
Maintainer-email: Poojan Shah <cs1221594@cse.iitd.ac.in>
License: MIT
Project-URL: Homepage, https://github.com/pcshah2004/kmeans-seeding
Project-URL: Documentation, https://kmeans-seeding.readthedocs.io
Project-URL: Repository, https://github.com/pcshah2004/kmeans-seeding
Project-URL: Issues, https://github.com/pcshah2004/kmeans-seeding/issues
Keywords: kmeans,clustering,machine-learning,initialization,seeding,rejection-sampling,mcmc
Classifier: Development Status :: 3 - Alpha
Classifier: Intended Audience :: Science/Research
Classifier: Intended Audience :: Developers
Classifier: License :: OSI Approved :: MIT License
Classifier: Programming Language :: C++
Classifier: Programming Language :: Python :: 3
Classifier: Programming Language :: Python :: 3.9
Classifier: Programming Language :: Python :: 3.10
Classifier: Programming Language :: Python :: 3.11
Classifier: Programming Language :: Python :: 3.12
Classifier: Topic :: Scientific/Engineering :: Artificial Intelligence
Classifier: Topic :: Software Development :: Libraries :: Python Modules
Classifier: Operating System :: POSIX :: Linux
Classifier: Operating System :: MacOS
Classifier: Operating System :: Microsoft :: Windows
Requires-Python: >=3.9
License-File: LICENSE
Requires-Dist: numpy>=1.20.0
Provides-Extra: faiss
Requires-Dist: faiss-cpu>=1.7.0; extra == "faiss"
Provides-Extra: dev
Requires-Dist: pytest>=7.0; extra == "dev"
Requires-Dist: pytest-cov>=4.0; extra == "dev"
Requires-Dist: scikit-learn>=1.0; extra == "dev"
Requires-Dist: black>=22.0; extra == "dev"
Requires-Dist: flake8>=5.0; extra == "dev"
Requires-Dist: mypy>=0.990; extra == "dev"
Provides-Extra: docs
Requires-Dist: sphinx>=5.0; extra == "docs"
Requires-Dist: sphinx-rtd-theme>=1.0; extra == "docs"
Requires-Dist: sphinx-copybutton>=0.5; extra == "docs"
Provides-Extra: all
Requires-Dist: kmeans-seeding[dev,docs,faiss]; extra == "all"
Dynamic: license-file
